{
  "name": "Middle Class Example",
  "timestamp": "2025-10-10T10:00:00.000Z",
  "currency": "USD",
  "accounts": [
    {
      "id": "checking-1",
      "type": "cash",
      "name": "Checking Account",
      "cash_balance": 10000
    },
    {
      "id": "savings-1",
      "type": "cash",
      "name": "Savings Account",
      "cash_balance": 25000
    },
    {
      "id": "401k-1",
      "type": "401k",
      "name": "401(k)",
      "holdings": [
        {
          "ticker": "VTI",
          "name": "Vanguard Total Stock Market Index Fund ETF",
          "units": 100,
          "price": 250
        },
        {
          "ticker": "BND",
          "name": "Vanguard Total Bond Market Index Fund ETF",
          "units": 50,
          "price": 75
        }
      ]
    },
    {
      "id": "roth-ira-1",
      "type": "roth",
      "name": "Roth IRA",
      "holdings": [
        {
          "ticker": "VOO",
          "name": "Vanguard S&P 500 ETF",
          "units": 50,
          "price": 400
        }
      ]
    }
  ],
  "real_estate": [
    {
      "id": "primary-residence",
      "value": 350000,
      "mortgage_balance": 250000
    }
  ],
  "contributions": [
    {
      "account_id": "401k-1",
      "amount": 1000,
      "frequency": "monthly"
    },
    {
      "account_id": "roth-ira-1",
      "amount": 500,
      "frequency": "monthly"
    }
  ],
  "expenses": [
    {
      "category": "Mortgage",
      "amount": 1800,
      "frequency": "monthly"
    },
    {
      "category": "Groceries",
      "amount": 600,
      "frequency": "monthly"
    },
    {
      "category": "Utilities",
      "amount": 300,
      "frequency": "monthly"
    }
  ],
  "retirement": {
    "expected_spend_monthly": 4000,
    "target_age": 65
  },
  "person": {
    "current_age": 40
  }
}